pyai_caching/__init__.py
pyai_caching/agent.py
pyai_caching/agent.pyi
pyai_caching/config.py
pyai_caching/config.pyi
pyai_caching/costs.py
pyai_caching/costs.pyi
pyai_caching/exceptions.py
pyai_caching/exceptions.pyi
pyai_caching/py.typed
pyai_caching/types.py
pyai_caching/types.pyi
pyai_caching-0.3.0.dist-info/METADATA
pyai_caching-0.3.0.dist-info/WHEEL
pyai_caching-0.3.0.dist-info/licenses/LICENSE
pyai_caching-0.3.0.dist-info/RECORD
