Metadata-Version: 2.4
Name: pyai-caching
Version: 0.3.0
Summary: Redis-based caching for Pydantic AI LLM agents with cost tracking
License: MIT
License-File: LICENSE
Keywords: llm,caching,redis,ai,cost-tracking
Author: Andrew de Jonge
Author-email: talkingtoaj@hotmail.com
Requires-Python: >=3.10,<4.0
Classifier: Development Status :: 4 - Beta
Classifier: Intended Audience :: Developers
Classifier: License :: OSI Approved :: MIT License
Classifier: Programming Language :: Python :: 3
Classifier: Programming Language :: Python :: 3.10
Classifier: Programming Language :: Python :: 3.11
Classifier: Programming Language :: Python :: 3.12
Classifier: Programming Language :: Python :: 3.13
Classifier: Programming Language :: Python :: 3.14
Classifier: Programming Language :: Python :: 3.9
Classifier: Topic :: Software Development :: Libraries :: Python Modules
Requires-Dist: pydantic
Requires-Dist: pydantic-ai
Requires-Dist: redis
Requires-Dist: typing-extensions
